pyexpose-0.1.2.dist-info/METADATA
pyexpose-0.1.2.dist-info/WHEEL
pyexpose/__init__.py
pyexpose/base/__init__.py
pyexpose/base/connector.py
pyexpose/base/logger.py
pyexpose/base/session.py
pyexpose/base/tunnel.py
pyexpose/providers/__init__.py
pyexpose/providers/localhost_run.py
pyexpose/providers/serveo.py
pyexpose-0.1.2.dist-info/RECORD
