Metadata-Version: 2.1
Name: pyexpose
Version: 0.1.2
Summary: Python library for creating SSH-based tunnels to expose local services, supporting commond providers like serveo.net and localhost.run. Supports modern Python syntax, asyncio, and context managers for ease of use
Author-Email: Harishankar Kumar <hari01584@gmail.com>
License: MIT
Requires-Python: >=3.8
Requires-Dist: asyncssh>=2.14.2
Requires-Dist: sphinx>=7.1.2
Requires-Dist: sphinx-rtd-theme>=2.0.0
Requires-Dist: rinohtype>=0.5.4
